MANIFEST.in
README.md
setup.cfg
setup.py
inspyre.egg-info/PKG-INFO
inspyre.egg-info/SOURCES.txt
inspyre.egg-info/dependency_links.txt
inspyre.egg-info/not-zip-safe
inspyre.egg-info/requires.txt
inspyre.egg-info/top_level.txt
saenews/README.md
saenews/Untitled.ipynb
saenews/__init__.py
saenews/dcsdcsdcdscsdc
saenews/haarcascade_frontalface_default.xml
saenews/image_template.py
saenews/insta.py
saenews/new.py
saenews/new.py~
saenews/sae2.py
saenews/sae2.py~
saenews/sae3.py
saenews/sae3.py~
saenews/saenews.py.save
saenews/saeutils.py
saenews/saeutils.py~
saenews/serv.py
saenews/sutils.py
saenews/sutils.py~
saenews/temp.py
saenews/temp.py~
saenews/templates.py
saenews/templates.py~
saenews/updater.py
saenews/utils.py
saenews/utils.py~
saenews/SM/fb.png
saenews/SM/search-cliparts.html
saenews/SM/tw.png
saenews/SM/twitter-clipart-logo-transparent-1-original.jpg
saenews/SM/twitter-clipart-logo-transparent-1-transparent.png
saenews/SM/twitter-clipart-logo-transparent-1.zip
saenews/SM/twitter-clipart-logo-transparent-2-original.png
saenews/SM/web.png
saenews/fonts/Antaro.ttf
saenews/fonts/BebasNeue-Bold.ttf
saenews/fonts/Charcoal.otf
saenews/fonts/Chunk Five Print.otf
saenews/fonts/ChunkFive-Regular.otf
saenews/fonts/CollegeBlock20-K5ql.ttf
saenews/fonts/Devant Horgen.otf
saenews/fonts/Devant Horgen.ttf
saenews/fonts/Freshman.ttf
saenews/fonts/HeadlinerNo45-59y8.ttf
saenews/fonts/Helvetica.ttf
saenews/fonts/License - READ THIS.txt
saenews/fonts/Microbrew-Soft-Eight.otf
saenews/fonts/Microbrew-Soft-Eleven.otf
saenews/fonts/Microbrew-Soft-Five-3D.otf
saenews/fonts/Microbrew-Soft-Five-Fill.otf
saenews/fonts/Microbrew-Soft-Five.otf
saenews/fonts/Microbrew-Soft-Four-3D.otf
saenews/fonts/Microbrew-Soft-Four.otf
saenews/fonts/Microbrew-Soft-Nine.otf
saenews/fonts/Microbrew-Soft-One-3D.otf
saenews/fonts/Microbrew-Soft-One-Combined.otf
saenews/fonts/Microbrew-Soft-One-Hatch-Shadow.otf
saenews/fonts/Microbrew-Soft-One-Hatch.otf
saenews/fonts/Microbrew-Soft-One-Inline.otf
saenews/fonts/Microbrew-Soft-One-Shadow.otf
saenews/fonts/Microbrew-Soft-One.otf
saenews/fonts/Microbrew-Soft-Ornaments.otf
saenews/fonts/Microbrew-Soft-Seven-3D.otf
